MergeHRISClient/__init__.py
MergeHRISClient/api_client.py
MergeHRISClient/configuration.py
MergeHRISClient/exceptions.py
MergeHRISClient/model_utils.py
MergeHRISClient/rest.py
MergeHRISClient/api/__init__.py
MergeHRISClient/api/account_details_api.py
MergeHRISClient/api/account_token_api.py
MergeHRISClient/api/available_actions_api.py
MergeHRISClient/api/bank_info_api.py
MergeHRISClient/api/benefits_api.py
MergeHRISClient/api/companies_api.py
MergeHRISClient/api/create_link_token_api.py
MergeHRISClient/api/deductions_api.py
MergeHRISClient/api/delete_account_api.py
MergeHRISClient/api/documents_api.py
MergeHRISClient/api/earnings_api.py
MergeHRISClient/api/employee_payroll_runs_api.py
MergeHRISClient/api/employees_api.py
MergeHRISClient/api/employments_api.py
MergeHRISClient/api/force_resync_api.py
MergeHRISClient/api/generate_key_api.py
MergeHRISClient/api/issues_api.py
MergeHRISClient/api/link_token_api.py
MergeHRISClient/api/linked_accounts_api.py
MergeHRISClient/api/locations_api.py
MergeHRISClient/api/passthrough_api.py
MergeHRISClient/api/pay_groups_api.py
MergeHRISClient/api/payroll_runs_api.py
MergeHRISClient/api/private_token_api.py
MergeHRISClient/api/regenerate_key_api.py
MergeHRISClient/api/reports_api.py
MergeHRISClient/api/sync_status_api.py
MergeHRISClient/api/tasks_api.py
MergeHRISClient/api/taxes_api.py
MergeHRISClient/api/teams_api.py
MergeHRISClient/api/time_off_api.py
MergeHRISClient/api/time_off_balance_api.py
MergeHRISClient/api/time_off_balances_api.py
MergeHRISClient/apis/__init__.py
MergeHRISClient/model/__init__.py
MergeHRISClient/model/account_details.py
MergeHRISClient/model/account_details_and_actions.py
MergeHRISClient/model/account_details_and_actions_integration.py
MergeHRISClient/model/account_details_and_actions_status_enum.py
MergeHRISClient/model/account_integration.py
MergeHRISClient/model/account_token.py
MergeHRISClient/model/account_type_enum.py
MergeHRISClient/model/available_actions.py
MergeHRISClient/model/bank_info.py
merge_hris_client-1.2.1.dist-info/METADATA
merge_hris_client-1.2.1.dist-info/WHEEL
merge_hris_client-1.2.1.dist-info/top_level.txt
merge_hris_client-1.2.1.dist-info/RECORD
