Metadata-Version: 2.1
Name: merge-hris-client
Version: 1.2.1
Summary: Merge HRIS API
Home-page: UNKNOWN
Author: Merge Team
Author-email: hello@merge.dev
License: UNKNOWN
Keywords: OpenAPI,OpenAPI-Generator,Merge HRIS API
Platform: UNKNOWN
Requires-Python: >=3.6
Requires-Dist: urllib3 (>=1.25.3)
Requires-Dist: python-dateutil
